LICENSE.md
MANIFEST.in
README.rst
setup.cfg
setup.py
versioneer.py
pswalker/__init__.py
pswalker/_version.py
pswalker/callbacks.py
pswalker/configure.py
pswalker/examples.py
pswalker/iterwalk.py
pswalker/path.py
pswalker/plan_stubs.py
pswalker/plans.py
pswalker/recovery.py
pswalker/skywalker.py
pswalker/suspenders.py
pswalker/watcher.py
pswalker.egg-info/PKG-INFO
pswalker.egg-info/SOURCES.txt
pswalker.egg-info/dependency_links.txt
pswalker.egg-info/top_level.txt
pswalker/sim/__init__.py
pswalker/sim/component.py
pswalker/sim/mirror.py
pswalker/sim/pim.py
pswalker/sim/pv.py
pswalker/sim/signal.py
pswalker/sim/sim.py
pswalker/sim/source.py
pswalker/sim/areadetector/__init__.py
pswalker/sim/areadetector/base.py
pswalker/sim/areadetector/cam.py
pswalker/sim/areadetector/detectors.py
pswalker/sim/areadetector/plugins.py
pswalker/tests/__init__.py
pswalker/tests/conftest.py
pswalker/tests/test_callbacks.py
pswalker/tests/test_examples.py
pswalker/tests/test_iterwalk.py
pswalker/tests/test_plan_stubs.py
pswalker/tests/test_plans.py
pswalker/tests/test_recovery.py
pswalker/tests/test_skywalker.py
pswalker/tests/test_suspenders.py
pswalker/tests/test_watcher.py
pswalker/tests/utils.py
pswalker/utils/__init__.py
pswalker/utils/argutils.py
pswalker/utils/exceptions.py